MANIFEST.in
setup.py
docs/HISTORY.txt
src/dolmen/__init__.py
src/dolmen.widget.image.egg-info/PKG-INFO
src/dolmen.widget.image.egg-info/SOURCES.txt
src/dolmen.widget.image.egg-info/dependency_links.txt
src/dolmen.widget.image.egg-info/entry_points.txt
src/dolmen.widget.image.egg-info/namespace_packages.txt
src/dolmen.widget.image.egg-info/not-zip-safe
src/dolmen.widget.image.egg-info/requires.txt
src/dolmen.widget.image.egg-info/top_level.txt
src/dolmen/widget/__init__.py
src/dolmen/widget/image/README.txt
src/dolmen/widget/image/__init__.py
src/dolmen/widget/image/configure.zcml
src/dolmen/widget/image/ftesting.zcml
src/dolmen/widget/image/tests.py
src/dolmen/widget/image/widget.py
src/dolmen/widget/image/templates/display.pt
src/dolmen/widget/image/templates/input.pt